Workbook

Sheet Parámetros
A1: Crédito hipotecario en UVR — Parámetros
A3: Monto del crédito (UVR) | B3: 1573589945
A4: Tasa base E.A. | B4: 0.083
A5: Número de cuotas | B5: 800
A6: Fecha primera cuota | B6: 44720
A7: Cuota esperada (UVR) — validación | B7: —
A8: Tramos de tasa
A9: Desde cuota | B9: Tasa E.A. | C9: i_m mensual | D9: Cuota del tramo (UVR)
A10: 1 | B10: 0.083 | C10: =(1+B10)^(1/12)-1 -> 0.0066667049 | D10: =Amortización!$C$5*C10/(1-(1+C10)^(-($B$5-A10+1))) -> 10542466
A11: 7 | B11: 0.0968 | C11: =(1+B11)^(1/12)-1 -> 0.0077294566 | D11: =Amortización!$C$11*C11/(1-(1+C11)^(-($B$5-A11+1))) -> 12187518
A13: Refrendamientos
A14: Diferencia cuota 1er tramo vs esperada | B14: =IF(ISNUMBER($B$7),D10-$B$7,"(sin referencia)") -> (sin referencia)
A15: ¿Cuota coincide (± 0,0001)? | B15: =IF(NOT(ISNUMBER($B$7)),"(sin ref.)",IF(ABS(D10-$B$7)<=0.0001,"OK","REVISAR")) -> (sin ref.)

Sheet Amortización
A1: Plan de amortización — cuota constante en UVR (sistema francés)
A4: N° cuota | B4: Fecha de pago | C4: Saldo inicial (UVR) | D4: Cuota total (UVR) | E4: Interés remuneratorio (UVR) | F4: Abono a capital (UVR) | G4: Saldo final (UVR)
A5: 1 | B5: =EDATE(Parámetros!$B$6,A5-1) -> 44720 | C5: =Parámetros!$B$3 -> 1573589945 | D5: =LOOKUP(A5,Parámetros!$A$10:$A$11,Parámetros!$D$10:$D$11) -> 10542466 | E5: =C5*LOOKUP(A5,Parámetros!$A$10:$A$11,Parámetros!$C$10:$C$11) -> 10490660 | F5: =D5-E5 -> 51805.804 | G5: =C5-F5 -> 1.5735381e+09
A6: 2 | B6: =EDATE(Parámetros!$B$6,A6-1) -> 44750 | C6: =G5 -> 1.5735381e+09 | D6: =LOOKUP(A6,Parámetros!$A$10:$A$11,Parámetros!$D$10:$D$11) -> 10542466 | E6: =C6*LOOKUP(A6,Parámetros!$A$10:$A$11,Parámetros!$C$10:$C$11) -> 10490314 | F6: =D6-E6 -> 52151.178 | G6: =C6-F6 -> 1.573486e+09
A7: 3 | B7: =EDATE(Parámetros!$B$6,A7-1) -> 44781 | C7: =G6 -> 1.573486e+09 | D7: =LOOKUP(A7,Parámetros!$A$10:$A$11,Parámetros!$D$10:$D$11) -> 10542466 | E7: =C7*LOOKUP(A7,Parámetros!$A$10:$A$11,Parámetros!$C$10:$C$11) -> 10489967 | F7: =D7-E7 -> 52498.854 | G7: =C7-F7 -> 1.5734335e+09
A8: 4 | B8: =EDATE(Parámetros!$B$6,A8-1) -> 44812 | C8: =G7 -> 1.5734335e+09 | D8: =LOOKUP(A8,Parámetros!$A$10:$A$11,Parámetros!$D$10:$D$11) -> 10542466 | E8: =C8*LOOKUP(A8,Parámetros!$A$10:$A$11,Parámetros!$C$10:$C$11) -> 10489617 | F8: =D8-E8 -> 52848.849 | G8: =C8-F8 -> 1.5733806e+09
A9: 5 | B9: =EDATE(Parámetros!$B$6,A9-1) -> 44842 | C9: =G8 -> 1.5733806e+09 | D9: =LOOKUP(A9,Parámetros!$A$10:$A$11,Parámetros!$D$10:$D$11) -> 10542466 | E9: =C9*LOOKUP(A9,Parámetros!$A$10:$A$11,Parámetros!$C$10:$C$11) -> 10489264 | F9: =D9-E9 -> 53201.176 | G9: =C9-F9 -> 1.5733274e+09
A10: 6 | B10: =EDATE(Parámetros!$B$6,A10-1) -> 44873 | C10: =G9 -> 1.5733274e+09 | D10: =LOOKUP(A10,Parámetros!$A$10:$A$11,Parámetros!$D$10:$D$11) -> 10542466 | E10: =C10*LOOKUP(A10,Parámetros!$A$10:$A$11,Parámetros!$C$10:$C$11) -> 10488910 | F10: =D10-E10 -> 53555.853 | G10: =C10-F10 -> 1.5732739e+09
A11: 7 | B11: =EDATE(Parámetros!$B$6,A11-1) -> 44903 | C11: =G10 -> 1.5732739e+09 | D11: =LOOKUP(A11,Parámetros!$A$10:$A$11,Parámetros!$D$10:$D$11) -> 12187518 | E11: =C11*LOOKUP(A11,Parámetros!$A$10:$A$11,Parámetros!$C$10:$C$11) -> 12160552 | F11: =D11-E11 -> 26965.98 | G11: =C11-F11 -> 1.5732469e+09
A12: 8 | B12: =EDATE(Parámetros!$B$6,A12-1) -> 44934 | C12: =G11 -> 1.5732469e+09 | D12: =LOOKUP(A12,Parámetros!$A$10:$A$11,Parámetros!$D$10:$D$11) -> 12187518 | E12: =C12*LOOKUP(A12,Parámetros!$A$10:$A$11,Parámetros!$C$10:$C$11) -> 12160344 | F12: =D12-E12 -> 27174.413 | G12: =C12-F12 -> 1.5732197e+09
A13: 9 | B13: =EDATE(Parámetros!$B$6,A13-1) -> 44965 | C13: =G12 -> 1.5732197e+09 | D13: =LOOKUP(A13,Parámetros!$A$10:$A$11,Parámetros!$D$10:$D$11) -> 12187518 | E13: =C13*LOOKUP(A13,Parámetros!$A$10:$A$11,Parámetros!$C$10:$C$11) -> 12160134 | F13: =D13-E13 -> 27384.456 | G13: =C13-F13 -> 1.5731924e+09
A14: 10 | B14: =EDATE(Parámetros!$B$6,A14-1) -> 44993 | C14: =G13 -> 1.5731924e+09 | D14: =LOOKUP(A14,Parámetros!$A$10:$A$11,Parámetros!$D$10:$D$11) -> 12187518 | E14: =C14*LOOKUP(A14,Parámetros!$A$10:$A$11,Parámetros!$C$10:$C$11) -> 12159922 | F14: =D14-E14 -> 27596.123 | G14: =C14-F14 -> 1.5731648e+09
A15: 11 | B15: =EDATE(Parámetros!$B$6,A15-1) -> 45024 | C15: =G14 -> 1.5731648e+09 | D15: =LOOKUP(A15,Parámetros!$A$10:$A$11,Parámetros!$D$10:$D$11) -> 12187518 | E15: =C15*LOOKUP(A15,Parámetros!$A$10:$A$11,Parámetros!$C$10:$C$11) -> 12159709 | F15: =D15-E15 -> 27809.426 | G15: =C15-F15 -> 1.573137e+09
A16: 12 | B16: =EDATE(Parámetros!$B$6,A16-1) -> 45054 | C16: =G15 -> 1.573137e+09 | D16: =LOOKUP(A16,Parámetros!$A$10:$A$11,Parámetros!$D$10:$D$11) -> 12187518 | E16: =C16*LOOKUP(A16,Parámetros!$A$10:$A$11,Parámetros!$C$10:$C$11) -> 12159494 | F16: =D16-E16 -> 28024.378 | G16: =C16-F16 -> 1.5731089e+09
A17: 13 | B17: =EDATE(Parámetros!$B$6,A17-1) -> 45085 | C17: =G16 -> 1.5731089e+09 | D17: =LOOKUP(A17,Parámetros!$A$10:$A$11,Parámetros!$D$10:$D$11) -> 12187518 | E17: =C17*LOOKUP(A17,Parámetros!$A$10:$A$11,Parámetros!$C$10:$C$11) -> 12159277 | F17: =D17-E17 -> 28240.991 | G17: =C17-F17 -> 1.5730807e+09
... A33: 29 | B33: =EDATE(Parámetros!$B$6,A33-1) -> 45573 | C33: =G32 -> 1.5726299e+09 | D33: =LOOKUP(A33,Parámetros!$A$10:$A$11,Parámetros!$D$10:$D$11) -> 12187518 | E33: =C33*LOOKUP(A33,Parámetros!$A$10:$A$11,Parámetros!$C$10:$C$11) -> 12155575 | F33: =D33-E33 -> 31943.551 | G33: =C33-F33 -> 1.572598e+09
A34: 30 | B34: =EDATE(Parámetros!$B$6,A34-1) -> 45604 | C34: =G33 -> 1.572598e+09 | D34: =E34+F34 -> 1.5847533e+09 | E34: =C34*LOOKUP(A34,Parámetros!$A$10:$A$11,Parámetros!$C$10:$C$11) -> 12155328 | F34: =C34 -> 1.572598e+09 | G34: =C34-F34 -> 0
B36: Total pagado (UVR) | D36: =SUM(D5:D34) -> 1.928321e+09
B37: Total intereses (UVR) | D37: =SUM(E5:E34) -> 3.5473106e+08
B38: Total capital amortizado (UVR) | D38: =SUM(F5:F34) -> 1573589945
B39: Refrendamientos (criterios de aceptación)
B40: Saldo final última cuota = 0 | D40: =IF(ABS(G34)<=0.0001,"OK","REVISAR") -> OK
B41: Capital amortizado = monto | D41: =IF(ABS(D38-Parámetros!$B$3)<=0.0001,"OK","REVISAR") -> OK
